odoo/addons/delivery_carrier_label_default/README.rst
odoo/addons/delivery_carrier_label_default/__init__.py
odoo/addons/delivery_carrier_label_default/__manifest__.py
odoo/addons/delivery_carrier_label_default/i18n/delivery_carrier_label_default.pot
odoo/addons/delivery_carrier_label_default/i18n/it.po
odoo/addons/delivery_carrier_label_default/models/__init__.py
odoo/addons/delivery_carrier_label_default/models/stock_picking.py
odoo/addons/delivery_carrier_label_default/readme/CONTRIBUTORS.md
odoo/addons/delivery_carrier_label_default/readme/CREDITS.md
odoo/addons/delivery_carrier_label_default/readme/DESCRIPTION.md
odoo/addons/delivery_carrier_label_default/readme/ROADMAP.md
odoo/addons/delivery_carrier_label_default/static/description/icon.svg
odoo/addons/delivery_carrier_label_default/static/description/index.html
odoo/addons/delivery_carrier_label_default/tests/__init__.py
odoo/addons/delivery_carrier_label_default/tests/common.py
odoo/addons/delivery_carrier_label_default/tests/test_print_label.py
odoo/addons/delivery_carrier_label_default/views/report_default_label.xml
odoo/addons/delivery_carrier_label_default/views/reports.xml
odoo_addon_delivery_carrier_label_default-18.0.1.0.0.5.dist-info/METADATA
odoo_addon_delivery_carrier_label_default-18.0.1.0.0.5.dist-info/WHEEL
odoo_addon_delivery_carrier_label_default-18.0.1.0.0.5.dist-info/top_level.txt
odoo_addon_delivery_carrier_label_default-18.0.1.0.0.5.dist-info/RECORD
